vxblastsms/__init__.py
vxblastsms/ussd.py
vxblastsms/tests/__init__.py
vxblastsms/tests/test_ussd.py
vxblastsms-0.1.0.dist-info/DESCRIPTION.rst
vxblastsms-0.1.0.dist-info/METADATA
vxblastsms-0.1.0.dist-info/metadata.json
vxblastsms-0.1.0.dist-info/RECORD
vxblastsms-0.1.0.dist-info/top_level.txt
vxblastsms-0.1.0.dist-info/WHEEL
