Metadata-Version: 2.0
Name: vxblastsms
Version: 0.1.0
Summary: An BlastSMS USSD transport for Vumi.
Home-page: http://github.com/westerncapelabs/vumi-blastsms
Author: Western Cape Labs
Author-email: devops@westerncapelabs.com
License: BSD
Platform: UNKNOWN
Classifier: Development Status :: 4 - Beta
Classifier: Intended Audience :: Developers
Classifier: License :: OSI Approved :: BSD License
Classifier: Operating System :: POSIX
Classifier: Programming Language :: Python
Classifier: Topic :: Software Development :: Libraries :: Python Modules
Classifier: Topic :: System :: Networking
Requires-Dist: vumi
Requires-Dist: Twisted (>=13.1.0)
